termux_ssh/__init__.py
termux_ssh/__main__.py
termux_ssh/termux.py
termux_ssh-1.2.0.dist-info/LICENSE
termux_ssh-1.2.0.dist-info/METADATA
termux_ssh-1.2.0.dist-info/WHEEL
termux_ssh-1.2.0.dist-info/RECORD
