Metadata-Version: 2.1
Name: termux-ssh
Version: 1.2.0
Summary: Termux SSH helps you to setup SSH server on termux application on android, which helps you to execute tasks remotely through terminal/cmd/powershell/termux
License: MIT
Author: Dhrumil Mistry
Author-email: 56185972+dmdhrumilmistry@users.noreply.github.com
Requires-Python: >=3.11,<4.0
Classifier: License :: OSI Approved :: MIT License
Classifier: Programming Language :: Python :: 3
Classifier: Programming Language :: Python :: 3.11
Classifier: Programming Language :: Python :: 3.12
Requires-Dist: colorama (>=0.4.6,<0.5.0)
Requires-Dist: netifaces (>=0.11.0,<0.12.0)
Requires-Dist: prettytable (>=3.10.0,<4.0.0)
